{
  "_format": "ethers-rs-sol-cache-3",
  "paths": {
    "artifacts": "out",
    "build_infos": "out/build-info",
    "sources": "contracts",
    "tests": "test",
    "scripts": "script",
    "libraries": [
      "lib",
      "node_modules"
    ]
  },
  "files": {
    "contracts/ERC1155Mock.sol": {
      "lastModificationDate": 1700731792531,
      "contentHash": "d41d8cd98f00b204e9800998ecf8427e",
      "sourceName": "contracts/ERC1155Mock.sol",
      "solcConfig": {
        "settings": {
          "optimizer": {
            "enabled": true,
            "runs": 200
          },
          "metadata": {
            "useLiteralContent": false,
            "bytecodeHash": "ipfs",
            "appendCBOR": true
          },
          "outputSelection": {
            "*": {
              "": [
                "ast"
              ],
              "*": [
                "abi",
                "evm.bytecode",
                "evm.deployedBytecode",
                "evm.methodIdentifiers",
                "metadata"
              ]
            }
          },
          "evmVersion": "paris",
          "libraries": {}
        }
      },
      "imports": [],
      "versionRequirement": null,
      "artifacts": {
        "ERC1155Mock": {
          "0.8.21+commit.d9974bed.Linux.gcc": "ERC1155Mock.sol/ERC1155Mock.json"
        }
      }
    },
    "contracts/ERC721Mock.sol": {
      "lastModificationDate": 1700731778563,
      "contentHash": "d41d8cd98f00b204e9800998ecf8427e",
      "sourceName": "contracts/ERC721Mock.sol",
      "solcConfig": {
        "settings": {
          "optimizer": {
            "enabled": true,
            "runs": 200
          },
          "metadata": {
            "useLiteralContent": false,
            "bytecodeHash": "ipfs",
            "appendCBOR": true
          },
          "outputSelection": {
            "*": {
              "": [
                "ast"
              ],
              "*": [
                "abi",
                "evm.bytecode",
                "evm.deployedBytecode",
                "evm.methodIdentifiers",
                "metadata"
              ]
            }
          },
          "evmVersion": "paris",
          "libraries": {}
        }
      },
      "imports": [],
      "versionRequirement": null,
      "artifacts": {
        "ERC721Mock": {
          "0.8.21+commit.d9974bed.Linux.gcc": "ERC721Mock.sol/ERC721Mock.json"
        }
      }
    },
    "contracts/IMastodonMarketplace.sol": {
      "lastModificationDate": 1700731440787,
      "contentHash": "2dd72c1726fb6bc884deed3d71477948",
      "sourceName": "contracts/IMastodonMarketplace.sol",
      "solcConfig": {
        "settings": {
          "optimizer": {
            "enabled": true,
            "runs": 200
          },
          "metadata": {
            "useLiteralContent": false,
            "bytecodeHash": "ipfs",
            "appendCBOR": true
          },
          "outputSelection": {
            "*": {
              "": [
                "ast"
              ],
              "*": [
                "abi",
                "evm.bytecode",
                "evm.deployedBytecode",
                "evm.methodIdentifiers",
                "metadata"
              ]
            }
          },
          "evmVersion": "paris",
          "libraries": {}
        }
      },
      "imports": [
        "node_modules/@openzeppelin/contracts/interfaces/IERC1155.sol",
        "node_modules/@openzeppelin/contracts/interfaces/IERC721.sol",
        "node_modules/@openzeppelin/contracts/token/ERC1155/IERC1155.sol",
        "node_modules/@openzeppelin/contracts/token/ERC721/IERC721.sol",
        "node_modules/@openzeppelin/contracts/utils/introspection/IERC165.sol"
      ],
      "versionRequirement": "^0.8.21",
      "artifacts": {
        "IMastodonMarketplace": {
          "0.8.21+commit.d9974bed.Linux.gcc": "IMastodonMarketplace.sol/IMastodonMarketplace.json"
        }
      }
    },
    "contracts/MastodonMarketplace.sol": {
      "lastModificationDate": 1700731464107,
      "contentHash": "0c7ee330cd2ab637d7be86ad7081843b",
      "sourceName": "contracts/MastodonMarketplace.sol",
      "solcConfig": {
        "settings": {
          "optimizer": {
            "enabled": true,
            "runs": 200
          },
          "metadata": {
            "useLiteralContent": false,
            "bytecodeHash": "ipfs",
            "appendCBOR": true
          },
          "outputSelection": {
            "*": {
              "": [
                "ast"
              ],
              "*": [
                "abi",
                "evm.bytecode",
                "evm.deployedBytecode",
                "evm.methodIdentifiers",
                "metadata"
              ]
            }
          },
          "evmVersion": "paris",
          "libraries": {}
        }
      },
      "imports": [
        "contracts/IMastodonMarketplace.sol",
        "node_modules/@openzeppelin/contracts/interfaces/IERC1155.sol",
        "node_modules/@openzeppelin/contracts/interfaces/IERC20.sol",
        "node_modules/@openzeppelin/contracts/interfaces/IERC721.sol",
        "node_modules/@openzeppelin/contracts/token/ERC1155/IERC1155.sol",
        "node_modules/@openzeppelin/contracts/token/ERC20/IERC20.sol",
        "node_modules/@openzeppelin/contracts/token/ERC721/IERC721.sol",
        "node_modules/@openzeppelin/contracts/utils/introspection/ERC165Checker.sol",
        "node_modules/@openzeppelin/contracts/utils/introspection/IERC165.sol",
        "node_modules/hardhat/console.sol"
      ],
      "versionRequirement": "^0.8.21",
      "artifacts": {
        "MastodonMarketplace": {
          "0.8.21+commit.d9974bed.Linux.gcc": "MastodonMarketplace.sol/MastodonMarketplace.json"
        }
      }
    },
    "contracts/xenBurn.sol": {
      "lastModificationDate": 1700672802467,
      "contentHash": "ec18cedae351ebba097a17fb6ee27749",
      "sourceName": "contracts/xenBurn.sol",
      "solcConfig": {
        "settings": {
          "optimizer": {
            "enabled": true,
            "runs": 200
          },
          "metadata": {
            "useLiteralContent": false,
            "bytecodeHash": "ipfs",
            "appendCBOR": true
          },
          "outputSelection": {
            "*": {
              "": [
                "ast"
              ],
              "*": [
                "abi",
                "evm.bytecode",
                "evm.deployedBytecode",
                "evm.methodIdentifiers",
                "metadata"
              ]
            }
          },
          "evmVersion": "paris",
          "libraries": {}
        }
      },
      "imports": [],
      "versionRequirement": null,
      "artifacts": {
        "xenBurn": {
          "0.8.21+commit.d9974bed.Linux.gcc": "xenBurn.sol/xenBurn.json"
        }
      }
    },
    "lib/forge-std/lib/ds-test/src/test.sol": {
      "lastModificationDate": 1697712502237,
      "contentHash": "9febff9d09f18af5306669dc276c4c43",
      "sourceName": "lib/forge-std/lib/ds-test/src/test.sol",
      "solcConfig": {
        "settings": {
          "optimizer": {
            "enabled": true,
            "runs": 200
          },
          "metadata": {
            "useLiteralContent": false,
            "bytecodeHash": "ipfs",
            "appendCBOR": true
          },
          "outputSelection": {
            "*": {
              "": [
                "ast"
              ],
              "*": [
                "abi",
                "evm.bytecode",
                "evm.deployedBytecode",
                "evm.methodIdentifiers",
                "metadata"
              ]
            }
          },
          "evmVersion": "paris",
          "libraries": {}
        }
      },
      "imports": [],
      "versionRequirement": ">=0.5.0",
      "artifacts": {
        "DSTest": {
          "0.8.21+commit.d9974bed.Linux.gcc": "test.sol/DSTest.json"
        }
      }
    },
    "lib/forge-std/src/Base.sol": {
      "lastModificationDate": 1697712502137,
      "contentHash": "ee13c050b1914464f1d3f90cde90204b",
      "sourceName": "lib/forge-std/src/Base.sol",
      "solcConfig": {
        "settings": {
          "optimizer": {
            "enabled": true,
            "runs": 200
          },
          "metadata": {
            "useLiteralContent": false,
            "bytecodeHash": "ipfs",
            "appendCBOR": true
          },
          "outputSelection": {
            "*": {
              "": [
                "ast"
              ],
              "*": [
                "abi",
                "evm.bytecode",
                "evm.deployedBytecode",
                "evm.methodIdentifiers",
                "metadata"
              ]
            }
          },
          "evmVersion": "paris",
          "libraries": {}
        }
      },
      "imports": [
        "lib/forge-std/src/StdStorage.sol",
        "lib/forge-std/src/Vm.sol"
      ],
      "versionRequirement": ">=0.6.2, <0.9.0",
      "artifacts": {
        "CommonBase": {
          "0.8.21+commit.d9974bed.Linux.gcc": "Base.sol/CommonBase.json"
        },
        "ScriptBase": {
          "0.8.21+commit.d9974bed.Linux.gcc": "Base.sol/ScriptBase.json"
        },
        "TestBase": {
          "0.8.21+commit.d9974bed.Linux.gcc": "Base.sol/TestBase.json"
        }
      }
    },
    "lib/forge-std/src/StdAssertions.sol": {
      "lastModificationDate": 1697712502137,
      "contentHash": "6cc2858240bcd443debbbf075490e325",
      "sourceName": "lib/forge-std/src/StdAssertions.sol",
      "solcConfig": {
        "settings": {
          "optimizer": {
            "enabled": true,
            "runs": 200
          },
          "metadata": {
            "useLiteralContent": false,
            "bytecodeHash": "ipfs",
            "appendCBOR": true
          },
          "outputSelection": {
            "*": {
              "": [
                "ast"
              ],
              "*": [
                "abi",
                "evm.bytecode",
                "evm.deployedBytecode",
                "evm.methodIdentifiers",
                "metadata"
              ]
            }
          },
          "evmVersion": "paris",
          "libraries": {}
        }
      },
      "imports": [
        "lib/forge-std/lib/ds-test/src/test.sol",
        "lib/forge-std/src/StdMath.sol"
      ],
      "versionRequirement": ">=0.6.2, <0.9.0",
      "artifacts": {
        "StdAssertions": {
          "0.8.21+commit.d9974bed.Linux.gcc": "StdAssertions.sol/StdAssertions.json"
        }
      }
    },
    "lib/forge-std/src/StdChains.sol": {
      "lastModificationDate": 1697712502137,
      "contentHash": "b0324b2e5a11948f852032aa293b3a05",
      "sourceName": "lib/forge-std/src/StdChains.sol",
      "solcConfig": {
        "settings": {
          "optimizer": {
            "enabled": true,
            "runs": 200
          },
          "metadata": {
            "useLiteralContent": false,
            "bytecodeHash": "ipfs",
            "appendCBOR": true
          },
          "outputSelection": {
            "*": {
              "": [
                "ast"
              ],
              "*": [
                "abi",
                "evm.bytecode",
                "evm.deployedBytecode",
                "evm.methodIdentifiers",
                "metadata"
              ]
            }
          },
          "evmVersion": "paris",
          "libraries": {}
        }
      },
      "imports": [
        "lib/forge-std/src/Vm.sol"
      ],
      "versionRequirement": ">=0.6.2, <0.9.0",
      "artifacts": {
        "StdChains": {
          "0.8.21+commit.d9974bed.Linux.gcc": "StdChains.sol/StdChains.json"
        }
      }
    },
    "lib/forge-std/src/StdCheats.sol": {
      "lastModificationDate": 1697712502137,
      "contentHash": "d984e2c76dae07bac1e292af2a5d4fd1",
      "sourceName": "lib/forge-std/src/StdCheats.sol",
      "solcConfig": {
        "settings": {
          "optimizer": {
            "enabled": true,
            "runs": 200
          },
          "metadata": {
            "useLiteralContent": false,
            "bytecodeHash": "ipfs",
            "appendCBOR": true
          },
          "outputSelection": {
            "*": {
              "": [
                "ast"
              ],
              "*": [
                "abi",
                "evm.bytecode",
                "evm.deployedBytecode",
                "evm.methodIdentifiers",
                "metadata"
              ]
            }
          },
          "evmVersion": "paris",
          "libraries": {}
        }
      },
      "imports": [
        "lib/forge-std/src/StdStorage.sol",
        "lib/forge-std/src/Vm.sol",
        "lib/forge-std/src/console2.sol"
      ],
      "versionRequirement": ">=0.6.2, <0.9.0",
      "artifacts": {
        "StdCheats": {
          "0.8.21+commit.d9974bed.Linux.gcc": "StdCheats.sol/StdCheats.json"
        },
        "StdCheatsSafe": {
          "0.8.21+commit.d9974bed.Linux.gcc": "StdCheats.sol/StdCheatsSafe.json"
        }
      }
    },
    "lib/forge-std/src/StdError.sol": {
      "lastModificationDate": 1697712502137,
      "contentHash": "64c896e1276a291776e5ea5aecb3870a",
      "sourceName": "lib/forge-std/src/StdError.sol",
      "solcConfig": {
        "settings": {
          "optimizer": {
            "enabled": true,
            "runs": 200
          },
          "metadata": {
            "useLiteralContent": false,
            "bytecodeHash": "ipfs",
            "appendCBOR": true
          },
          "outputSelection": {
            "*": {
              "": [
                "ast"
              ],
              "*": [
                "abi",
                "evm.bytecode",
                "evm.deployedBytecode",
                "evm.methodIdentifiers",
                "metadata"
              ]
            }
          },
          "evmVersion": "paris",
          "libraries": {}
        }
      },
      "imports": [],
      "versionRequirement": ">=0.6.2, <0.9.0",
      "artifacts": {
        "stdError": {
          "0.8.21+commit.d9974bed.Linux.gcc": "StdError.sol/stdError.json"
        }
      }
    },
    "lib/forge-std/src/StdInvariant.sol": {
      "lastModificationDate": 1697712502137,
      "contentHash": "0a580d6fac69e9d4b6504f747f3c0c24",
      "sourceName": "lib/forge-std/src/StdInvariant.sol",
      "solcConfig": {
        "settings": {
          "optimizer": {
            "enabled": true,
            "runs": 200
          },
          "metadata": {
            "useLiteralContent": false,
            "bytecodeHash": "ipfs",
            "appendCBOR": true
          },
          "outputSelection": {
            "*": {
              "": [
                "ast"
              ],
              "*": [
                "abi",
                "evm.bytecode",
                "evm.deployedBytecode",
                "evm.methodIdentifiers",
                "metadata"
              ]
            }
          },
          "evmVersion": "paris",
          "libraries": {}
        }
      },
      "imports": [],
      "versionRequirement": ">=0.6.2, <0.9.0",
      "artifacts": {
        "StdInvariant": {
          "0.8.21+commit.d9974bed.Linux.gcc": "StdInvariant.sol/StdInvariant.json"
        }
      }
    },
    "lib/forge-std/src/StdJson.sol": {
      "lastModificationDate": 1697712502137,
      "contentHash": "a341308627b7eeab7589534daad58186",
      "sourceName": "lib/forge-std/src/StdJson.sol",
      "solcConfig": {
        "settings": {
          "optimizer": {
            "enabled": true,
            "runs": 200
          },
          "metadata": {
            "useLiteralContent": false,
            "bytecodeHash": "ipfs",
            "appendCBOR": true
          },
          "outputSelection": {
            "*": {
              "": [
                "ast"
              ],
              "*": [
                "abi",
                "evm.bytecode",
                "evm.deployedBytecode",
                "evm.methodIdentifiers",
                "metadata"
              ]
            }
          },
          "evmVersion": "paris",
          "libraries": {}
        }
      },
      "imports": [
        "lib/forge-std/src/Vm.sol"
      ],
      "versionRequirement": ">=0.6.0, <0.9.0",
      "artifacts": {
        "stdJson": {
          "0.8.21+commit.d9974bed.Linux.gcc": "StdJson.sol/stdJson.json"
        }
      }
    },
    "lib/forge-std/src/StdMath.sol": {
      "lastModificationDate": 1697712502137,
      "contentHash": "9da8f453eba6bb98f3d75bc6822bfb29",
      "sourceName": "lib/forge-std/src/StdMath.sol",
      "solcConfig": {
        "settings": {
          "optimizer": {
            "enabled": true,
            "runs": 200
          },
          "metadata": {
            "useLiteralContent": false,
            "bytecodeHash": "ipfs",
            "appendCBOR": true
          },
          "outputSelection": {
            "*": {
              "": [
                "ast"
              ],
              "*": [
                "abi",
                "evm.bytecode",
                "evm.deployedBytecode",
                "evm.methodIdentifiers",
                "metadata"
              ]
            }
          },
          "evmVersion": "paris",
          "libraries": {}
        }
      },
      "imports": [],
      "versionRequirement": ">=0.6.2, <0.9.0",
      "artifacts": {
        "stdMath": {
          "0.8.21+commit.d9974bed.Linux.gcc": "StdMath.sol/stdMath.json"
        }
      }
    },
    "lib/forge-std/src/StdStorage.sol": {
      "lastModificationDate": 1697712502137,
      "contentHash": "abd6f3379e6e2a7979b18abc21aea0c1",
      "sourceName": "lib/forge-std/src/StdStorage.sol",
      "solcConfig": {
        "settings": {
          "optimizer": {
            "enabled": true,
            "runs": 200
          },
          "metadata": {
            "useLiteralContent": false,
            "bytecodeHash": "ipfs",
            "appendCBOR": true
          },
          "outputSelection": {
            "*": {
              "": [
                "ast"
              ],
              "*": [
                "abi",
                "evm.bytecode",
                "evm.deployedBytecode",
                "evm.methodIdentifiers",
                "metadata"
              ]
            }
          },
          "evmVersion": "paris",
          "libraries": {}
        }
      },
      "imports": [
        "lib/forge-std/src/Vm.sol"
      ],
      "versionRequirement": ">=0.6.2, <0.9.0",
      "artifacts": {
        "stdStorage": {
          "0.8.21+commit.d9974bed.Linux.gcc": "StdStorage.sol/stdStorage.json"
        },
        "stdStorageSafe": {
          "0.8.21+commit.d9974bed.Linux.gcc": "StdStorage.sol/stdStorageSafe.json"
        }
      }
    },
    "lib/forge-std/src/StdStyle.sol": {
      "lastModificationDate": 1697712502141,
      "contentHash": "6281165a12aa639705c691fccefd855e",
      "sourceName": "lib/forge-std/src/StdStyle.sol",
      "solcConfig": {
        "settings": {
          "optimizer": {
            "enabled": true,
            "runs": 200
          },
          "metadata": {
            "useLiteralContent": false,
            "bytecodeHash": "ipfs",
            "appendCBOR": true
          },
          "outputSelection": {
            "*": {
              "": [
                "ast"
              ],
              "*": [
                "abi",
                "evm.bytecode",
                "evm.deployedBytecode",
                "evm.methodIdentifiers",
                "metadata"
              ]
            }
          },
          "evmVersion": "paris",
          "libraries": {}
        }
      },
      "imports": [
        "lib/forge-std/src/Vm.sol"
      ],
      "versionRequirement": ">=0.4.22, <0.9.0",
      "artifacts": {
        "StdStyle": {
          "0.8.21+commit.d9974bed.Linux.gcc": "StdStyle.sol/StdStyle.json"
        }
      }
    },
    "lib/forge-std/src/StdUtils.sol": {
      "lastModificationDate": 1697712502141,
      "contentHash": "3ce83748fd76644688f916c9cced545b",
      "sourceName": "lib/forge-std/src/StdUtils.sol",
      "solcConfig": {
        "settings": {
          "optimizer": {
            "enabled": true,
            "runs": 200
          },
          "metadata": {
            "useLiteralContent": false,
            "bytecodeHash": "ipfs",
            "appendCBOR": true
          },
          "outputSelection": {
            "*": {
              "": [
                "ast"
              ],
              "*": [
                "abi",
                "evm.bytecode",
                "evm.deployedBytecode",
                "evm.methodIdentifiers",
                "metadata"
              ]
            }
          },
          "evmVersion": "paris",
          "libraries": {}
        }
      },
      "imports": [
        "lib/forge-std/src/Vm.sol",
        "lib/forge-std/src/interfaces/IMulticall3.sol"
      ],
      "versionRequirement": ">=0.6.2, <0.9.0",
      "artifacts": {
        "StdUtils": {
          "0.8.21+commit.d9974bed.Linux.gcc": "StdUtils.sol/StdUtils.json"
        }
      }
    },
    "lib/forge-std/src/Test.sol": {
      "lastModificationDate": 1697712502141,
      "contentHash": "15866901137b5670eabf31362523bd28",
      "sourceName": "lib/forge-std/src/Test.sol",
      "solcConfig": {
        "settings": {
          "optimizer": {
            "enabled": true,
            "runs": 200
          },
          "metadata": {
            "useLiteralContent": false,
            "bytecodeHash": "ipfs",
            "appendCBOR": true
          },
          "outputSelection": {
            "*": {
              "": [
                "ast"
              ],
              "*": [
                "abi",
                "evm.bytecode",
                "evm.deployedBytecode",
                "evm.methodIdentifiers",
                "metadata"
              ]
            }
          },
          "evmVersion": "paris",
          "libraries": {}
        }
      },
      "imports": [
        "lib/forge-std/lib/ds-test/src/test.sol",
        "lib/forge-std/src/Base.sol",
        "lib/forge-std/src/StdAssertions.sol",
        "lib/forge-std/src/StdChains.sol",
        "lib/forge-std/src/StdCheats.sol",
        "lib/forge-std/src/StdError.sol",
        "lib/forge-std/src/StdInvariant.sol",
        "lib/forge-std/src/StdJson.sol",
        "lib/forge-std/src/StdMath.sol",
        "lib/forge-std/src/StdStorage.sol",
        "lib/forge-std/src/StdStyle.sol",
        "lib/forge-std/src/StdUtils.sol",
        "lib/forge-std/src/Vm.sol",
        "lib/forge-std/src/console.sol",
        "lib/forge-std/src/console2.sol",
        "lib/forge-std/src/interfaces/IMulticall3.sol",
        "lib/forge-std/src/safeconsole.sol"
      ],
      "versionRequirement": ">=0.6.2, <0.9.0",
      "artifacts": {
        "Test": {
          "0.8.21+commit.d9974bed.Linux.gcc": "Test.sol/Test.json"
        }
      }
    },
    "lib/forge-std/src/Vm.sol": {
      "lastModificationDate": 1697712502141,
      "contentHash": "eff2556a384c025f56150fb3f78de858",
      "sourceName": "lib/forge-std/src/Vm.sol",
      "solcConfig": {
        "settings": {
          "optimizer": {
            "enabled": true,
            "runs": 200
          },
          "metadata": {
            "useLiteralContent": false,
            "bytecodeHash": "ipfs",
            "appendCBOR": true
          },
          "outputSelection": {
            "*": {
              "": [
                "ast"
              ],
              "*": [
                "abi",
                "evm.bytecode",
                "evm.deployedBytecode",
                "evm.methodIdentifiers",
                "metadata"
              ]
            }
          },
          "evmVersion": "paris",
          "libraries": {}
        }
      },
      "imports": [],
      "versionRequirement": ">=0.6.2, <0.9.0",
      "artifacts": {
        "Vm": {
          "0.8.21+commit.d9974bed.Linux.gcc": "Vm.sol/Vm.json"
        },
        "VmSafe": {
          "0.8.21+commit.d9974bed.Linux.gcc": "Vm.sol/VmSafe.json"
        }
      }
    },
    "lib/forge-std/src/console.sol": {
      "lastModificationDate": 1697712502141,
      "contentHash": "100b8a33b917da1147740d7ab8b0ded3",
      "sourceName": "lib/forge-std/src/console.sol",
      "solcConfig": {
        "settings": {
          "optimizer": {
            "enabled": true,
            "runs": 200
          },
          "metadata": {
            "useLiteralContent": false,
            "bytecodeHash": "ipfs",
            "appendCBOR": true
          },
          "outputSelection": {
            "*": {
              "": [
                "ast"
              ],
              "*": [
                "abi",
                "evm.bytecode",
                "evm.deployedBytecode",
                "evm.methodIdentifiers",
                "metadata"
              ]
            }
          },
          "evmVersion": "paris",
          "libraries": {}
        }
      },
      "imports": [],
      "versionRequirement": ">=0.4.22, <0.9.0",
      "artifacts": {
        "console": {
          "0.8.21+commit.d9974bed.Linux.gcc": "src/console.sol/console.json"
        }
      }
    },
    "lib/forge-std/src/console2.sol": {
      "lastModificationDate": 1697712502141,
      "contentHash": "491ca717c1915995e78cc361485a3067",
      "sourceName": "lib/forge-std/src/console2.sol",
      "solcConfig": {
        "settings": {
          "optimizer": {
            "enabled": true,
            "runs": 200
          },
          "metadata": {
            "useLiteralContent": false,
            "bytecodeHash": "ipfs",
            "appendCBOR": true
          },
          "outputSelection": {
            "*": {
              "": [
                "ast"
              ],
              "*": [
                "abi",
                "evm.bytecode",
                "evm.deployedBytecode",
                "evm.methodIdentifiers",
                "metadata"
              ]
            }
          },
          "evmVersion": "paris",
          "libraries": {}
        }
      },
      "imports": [],
      "versionRequirement": ">=0.4.22, <0.9.0",
      "artifacts": {
        "console2": {
          "0.8.21+commit.d9974bed.Linux.gcc": "console2.sol/console2.json"
        }
      }
    },
    "lib/forge-std/src/interfaces/IMulticall3.sol": {
      "lastModificationDate": 1697712502141,
      "contentHash": "7b131ca1ca32ef6378b7b9ad5488b901",
      "sourceName": "lib/forge-std/src/interfaces/IMulticall3.sol",
      "solcConfig": {
        "settings": {
          "optimizer": {
            "enabled": true,
            "runs": 200
          },
          "metadata": {
            "useLiteralContent": false,
            "bytecodeHash": "ipfs",
            "appendCBOR": true
          },
          "outputSelection": {
            "*": {
              "": [
                "ast"
              ],
              "*": [
                "abi",
                "evm.bytecode",
                "evm.deployedBytecode",
                "evm.methodIdentifiers",
                "metadata"
              ]
            }
          },
          "evmVersion": "paris",
          "libraries": {}
        }
      },
      "imports": [],
      "versionRequirement": ">=0.6.2, <0.9.0",
      "artifacts": {
        "IMulticall3": {
          "0.8.21+commit.d9974bed.Linux.gcc": "IMulticall3.sol/IMulticall3.json"
        }
      }
    },
    "lib/forge-std/src/safeconsole.sol": {
      "lastModificationDate": 1697712502141,
      "contentHash": "ac3b1bf5a444db5db3656021830258a8",
      "sourceName": "lib/forge-std/src/safeconsole.sol",
      "solcConfig": {
        "settings": {
          "optimizer": {
            "enabled": true,
            "runs": 200
          },
          "metadata": {
            "useLiteralContent": false,
            "bytecodeHash": "ipfs",
            "appendCBOR": true
          },
          "outputSelection": {
            "*": {
              "": [
                "ast"
              ],
              "*": [
                "abi",
                "evm.bytecode",
                "evm.deployedBytecode",
                "evm.methodIdentifiers",
                "metadata"
              ]
            }
          },
          "evmVersion": "paris",
          "libraries": {}
        }
      },
      "imports": [],
      "versionRequirement": ">=0.6.2, <0.9.0",
      "artifacts": {
        "safeconsole": {
          "0.8.21+commit.d9974bed.Linux.gcc": "safeconsole.sol/safeconsole.json"
        }
      }
    },
    "node_modules/@openzeppelin/contracts/interfaces/IERC1155.sol": {
      "lastModificationDate": 1698148236798,
      "contentHash": "9073ad0d8f70749583dff4c93336fb1a",
      "sourceName": "node_modules/@openzeppelin/contracts/interfaces/IERC1155.sol",
      "solcConfig": {
        "settings": {
          "optimizer": {
            "enabled": true,
            "runs": 200
          },
          "metadata": {
            "useLiteralContent": false,
            "bytecodeHash": "ipfs",
            "appendCBOR": true
          },
          "outputSelection": {
            "*": {
              "": [
                "ast"
              ],
              "*": [
                "abi",
                "evm.bytecode",
                "evm.deployedBytecode",
                "evm.methodIdentifiers",
                "metadata"
              ]
            }
          },
          "evmVersion": "paris",
          "libraries": {}
        }
      },
      "imports": [
        "node_modules/@openzeppelin/contracts/token/ERC1155/IERC1155.sol",
        "node_modules/@openzeppelin/contracts/utils/introspection/IERC165.sol"
      ],
      "versionRequirement": "^0.8.20",
      "artifacts": {
        "IERC1155": {
          "0.8.21+commit.d9974bed.Linux.gcc": "interfaces/IERC1155.sol/IERC1155.json"
        }
      }
    },
    "node_modules/@openzeppelin/contracts/interfaces/IERC20.sol": {
      "lastModificationDate": 1698148236802,
      "contentHash": "79af12d64eacc7d77b9ee2ac4b4d51ee",
      "sourceName": "node_modules/@openzeppelin/contracts/interfaces/IERC20.sol",
      "solcConfig": {
        "settings": {
          "optimizer": {
            "enabled": true,
            "runs": 200
          },
          "metadata": {
            "useLiteralContent": false,
            "bytecodeHash": "ipfs",
            "appendCBOR": true
          },
          "outputSelection": {
            "*": {
              "": [
                "ast"
              ],
              "*": [
                "abi",
                "evm.bytecode",
                "evm.deployedBytecode",
                "evm.methodIdentifiers",
                "metadata"
              ]
            }
          },
          "evmVersion": "paris",
          "libraries": {}
        }
      },
      "imports": [
        "node_modules/@openzeppelin/contracts/token/ERC20/IERC20.sol"
      ],
      "versionRequirement": "^0.8.20",
      "artifacts": {
        "IERC20": {
          "0.8.21+commit.d9974bed.Linux.gcc": "interfaces/IERC20.sol/IERC20.json"
        }
      }
    },
    "node_modules/@openzeppelin/contracts/interfaces/IERC721.sol": {
      "lastModificationDate": 1698148236802,
      "contentHash": "d8d23fc2f55ed934d1a1b91c9afd8526",
      "sourceName": "node_modules/@openzeppelin/contracts/interfaces/IERC721.sol",
      "solcConfig": {
        "settings": {
          "optimizer": {
            "enabled": true,
            "runs": 200
          },
          "metadata": {
            "useLiteralContent": false,
            "bytecodeHash": "ipfs",
            "appendCBOR": true
          },
          "outputSelection": {
            "*": {
              "": [
                "ast"
              ],
              "*": [
                "abi",
                "evm.bytecode",
                "evm.deployedBytecode",
                "evm.methodIdentifiers",
                "metadata"
              ]
            }
          },
          "evmVersion": "paris",
          "libraries": {}
        }
      },
      "imports": [
        "node_modules/@openzeppelin/contracts/token/ERC721/IERC721.sol",
        "node_modules/@openzeppelin/contracts/utils/introspection/IERC165.sol"
      ],
      "versionRequirement": "^0.8.20",
      "artifacts": {
        "IERC721": {
          "0.8.21+commit.d9974bed.Linux.gcc": "interfaces/IERC721.sol/IERC721.json"
        }
      }
    },
    "node_modules/@openzeppelin/contracts/token/ERC1155/IERC1155.sol": {
      "lastModificationDate": 1698148236798,
      "contentHash": "b091cae7bc6a906ec5956ad0dcd55ae0",
      "sourceName": "node_modules/@openzeppelin/contracts/token/ERC1155/IERC1155.sol",
      "solcConfig": {
        "settings": {
          "optimizer": {
            "enabled": true,
            "runs": 200
          },
          "metadata": {
            "useLiteralContent": false,
            "bytecodeHash": "ipfs",
            "appendCBOR": true
          },
          "outputSelection": {
            "*": {
              "": [
                "ast"
              ],
              "*": [
                "abi",
                "evm.bytecode",
                "evm.deployedBytecode",
                "evm.methodIdentifiers",
                "metadata"
              ]
            }
          },
          "evmVersion": "paris",
          "libraries": {}
        }
      },
      "imports": [
        "node_modules/@openzeppelin/contracts/utils/introspection/IERC165.sol"
      ],
      "versionRequirement": "^0.8.20",
      "artifacts": {
        "IERC1155": {
          "0.8.21+commit.d9974bed.Linux.gcc": "IERC1155.sol/IERC1155.json"
        }
      }
    },
    "node_modules/@openzeppelin/contracts/token/ERC20/IERC20.sol": {
      "lastModificationDate": 1698148236802,
      "contentHash": "5517c8678c18eb1a8ba58810e7ca39ca",
      "sourceName": "node_modules/@openzeppelin/contracts/token/ERC20/IERC20.sol",
      "solcConfig": {
        "settings": {
          "optimizer": {
            "enabled": true,
            "runs": 200
          },
          "metadata": {
            "useLiteralContent": false,
            "bytecodeHash": "ipfs",
            "appendCBOR": true
          },
          "outputSelection": {
            "*": {
              "": [
                "ast"
              ],
              "*": [
                "abi",
                "evm.bytecode",
                "evm.deployedBytecode",
                "evm.methodIdentifiers",
                "metadata"
              ]
            }
          },
          "evmVersion": "paris",
          "libraries": {}
        }
      },
      "imports": [],
      "versionRequirement": "^0.8.20",
      "artifacts": {
        "IERC20": {
          "0.8.21+commit.d9974bed.Linux.gcc": "IERC20.sol/IERC20.json"
        }
      }
    },
    "node_modules/@openzeppelin/contracts/token/ERC721/IERC721.sol": {
      "lastModificationDate": 1698148236802,
      "contentHash": "5df8fdb527e563085847cad29e3c5f2e",
      "sourceName": "node_modules/@openzeppelin/contracts/token/ERC721/IERC721.sol",
      "solcConfig": {
        "settings": {
          "optimizer": {
            "enabled": true,
            "runs": 200
          },
          "metadata": {
            "useLiteralContent": false,
            "bytecodeHash": "ipfs",
            "appendCBOR": true
          },
          "outputSelection": {
            "*": {
              "": [
                "ast"
              ],
              "*": [
                "abi",
                "evm.bytecode",
                "evm.deployedBytecode",
                "evm.methodIdentifiers",
                "metadata"
              ]
            }
          },
          "evmVersion": "paris",
          "libraries": {}
        }
      },
      "imports": [
        "node_modules/@openzeppelin/contracts/utils/introspection/IERC165.sol"
      ],
      "versionRequirement": "^0.8.20",
      "artifacts": {
        "IERC721": {
          "0.8.21+commit.d9974bed.Linux.gcc": "IERC721.sol/IERC721.json"
        }
      }
    },
    "node_modules/@openzeppelin/contracts/utils/introspection/ERC165Checker.sol": {
      "lastModificationDate": 1698148236790,
      "contentHash": "39cb7ad93657f9f444653cf94d6fc392",
      "sourceName": "node_modules/@openzeppelin/contracts/utils/introspection/ERC165Checker.sol",
      "solcConfig": {
        "settings": {
          "optimizer": {
            "enabled": true,
            "runs": 200
          },
          "metadata": {
            "useLiteralContent": false,
            "bytecodeHash": "ipfs",
            "appendCBOR": true
          },
          "outputSelection": {
            "*": {
              "": [
                "ast"
              ],
              "*": [
                "abi",
                "evm.bytecode",
                "evm.deployedBytecode",
                "evm.methodIdentifiers",
                "metadata"
              ]
            }
          },
          "evmVersion": "paris",
          "libraries": {}
        }
      },
      "imports": [
        "node_modules/@openzeppelin/contracts/utils/introspection/IERC165.sol"
      ],
      "versionRequirement": "^0.8.20",
      "artifacts": {
        "ERC165Checker": {
          "0.8.21+commit.d9974bed.Linux.gcc": "ERC165Checker.sol/ERC165Checker.json"
        }
      }
    },
    "node_modules/@openzeppelin/contracts/utils/introspection/IERC165.sol": {
      "lastModificationDate": 1698148236802,
      "contentHash": "de0163561b417b800d01749cbbe2147e",
      "sourceName": "node_modules/@openzeppelin/contracts/utils/introspection/IERC165.sol",
      "solcConfig": {
        "settings": {
          "optimizer": {
            "enabled": true,
            "runs": 200
          },
          "metadata": {
            "useLiteralContent": false,
            "bytecodeHash": "ipfs",
            "appendCBOR": true
          },
          "outputSelection": {
            "*": {
              "": [
                "ast"
              ],
              "*": [
                "abi",
                "evm.bytecode",
                "evm.deployedBytecode",
                "evm.methodIdentifiers",
                "metadata"
              ]
            }
          },
          "evmVersion": "paris",
          "libraries": {}
        }
      },
      "imports": [],
      "versionRequirement": "^0.8.20",
      "artifacts": {
        "IERC165": {
          "0.8.21+commit.d9974bed.Linux.gcc": "IERC165.sol/IERC165.json"
        }
      }
    },
    "node_modules/hardhat/console.sol": {
      "lastModificationDate": 1698144193846,
      "contentHash": "896f68942c3a20e9ae3c3c5bfd3add54",
      "sourceName": "node_modules/hardhat/console.sol",
      "solcConfig": {
        "settings": {
          "optimizer": {
            "enabled": true,
            "runs": 200
          },
          "metadata": {
            "useLiteralContent": false,
            "bytecodeHash": "ipfs",
            "appendCBOR": true
          },
          "outputSelection": {
            "*": {
              "": [
                "ast"
              ],
              "*": [
                "abi",
                "evm.bytecode",
                "evm.deployedBytecode",
                "evm.methodIdentifiers",
                "metadata"
              ]
            }
          },
          "evmVersion": "paris",
          "libraries": {}
        }
      },
      "imports": [],
      "versionRequirement": ">=0.4.22, <0.9.0",
      "artifacts": {
        "console": {
          "0.8.21+commit.d9974bed.Linux.gcc": "console.sol/console.json"
        }
      }
    },
    "test/accesslists.t.sol": {
      "lastModificationDate": 1701107563919,
      "contentHash": "03390d646039cc7a126219957b94c181",
      "sourceName": "test/accesslists.t.sol",
      "solcConfig": {
        "settings": {
          "optimizer": {
            "enabled": true,
            "runs": 200
          },
          "metadata": {
            "useLiteralContent": false,
            "bytecodeHash": "ipfs",
            "appendCBOR": true
          },
          "outputSelection": {
            "*": {
              "": [
                "ast"
              ],
              "*": [
                "abi",
                "evm.bytecode",
                "evm.deployedBytecode",
                "evm.methodIdentifiers",
                "metadata"
              ]
            }
          },
          "evmVersion": "paris",
          "libraries": {}
        }
      },
      "imports": [
        "lib/forge-std/lib/ds-test/src/test.sol",
        "lib/forge-std/src/Base.sol",
        "lib/forge-std/src/StdAssertions.sol",
        "lib/forge-std/src/StdChains.sol",
        "lib/forge-std/src/StdCheats.sol",
        "lib/forge-std/src/StdError.sol",
        "lib/forge-std/src/StdInvariant.sol",
        "lib/forge-std/src/StdJson.sol",
        "lib/forge-std/src/StdMath.sol",
        "lib/forge-std/src/StdStorage.sol",
        "lib/forge-std/src/StdStyle.sol",
        "lib/forge-std/src/StdUtils.sol",
        "lib/forge-std/src/Test.sol",
        "lib/forge-std/src/Vm.sol",
        "lib/forge-std/src/console.sol",
        "lib/forge-std/src/console2.sol",
        "lib/forge-std/src/interfaces/IMulticall3.sol",
        "lib/forge-std/src/safeconsole.sol"
      ],
      "versionRequirement": "=0.8.21",
      "artifacts": {
        "ContractBTest": {
          "0.8.21+commit.d9974bed.Linux.gcc": "accesslists.t.sol/ContractBTest.json"
        },
        "ErrorsTest": {
          "0.8.21+commit.d9974bed.Linux.gcc": "accesslists.t.sol/ErrorsTest.json"
        }
      }
    }
  }
}